<Properties StartupConfiguration="{B072B78C-6B58-417E-8344-960546978915}|Default">
  <MonoDevelop.Ide.ItemProperties.OdeToFood PreferredExecutionTarget="/Applications/Safari.app" />
  <MonoDevelop.Ide.Workbench>
    <Pads>
      <Pad Id="ProjectPad">
        <State name="__root__">
          <Node name="OdeToFood" expanded="True">
            <Node name="OdeToFood" expanded="True">
              <Node name="Pages" expanded="True">
                <Node name="Restaurants" expanded="True" selected="True" />
              </Node>
              <Node name="appsettings.json" expanded="True" />
            </Node>
            <Node name="OdeToFood.Core" expanded="True" />
            <Node name="OdeToFood.Data" expanded="True" />
          </Node>
        </State>
      </Pad>
    </Pads>
  </MonoDevelop.Ide.Workbench>
  <MonoDevelop.Ide.DebuggingService.PinnedWatches />
  <MonoDevelop.Ide.Workspace ActiveConfiguration="Debug" />
  <MonoDevelop.Ide.DebuggingService.Breakpoints>
    <BreakpointStore />
  </MonoDevelop.Ide.DebuggingService.Breakpoints>
  <MultiItemStartupConfigurations />
</Properties>